src/__init__.py
src/core/exceptions.py
src/data_io.py
src/main.py
src/translate.py
butran-0.1.0.dist-info/METADATA
butran-0.1.0.dist-info/WHEEL
butran-0.1.0.dist-info/RECORD
