Metadata-Version: 2.1
Name: butran
Version: 0.1.0
Summary: Bulk translator catered to translating machine learning benchmark sets.
Author: Marten Koopmans
Author-email: 36400337+Mkoopm@users.noreply.github.com
Requires-Python: >=3.11.7,<3.12.0
Classifier: Programming Language :: Python :: 3
Requires-Dist: argh (>=0.31.1,<0.32.0)
Requires-Dist: beir (>=2.0.0,<3.0.0)
Requires-Dist: sacremoses (>=0.1.1,<0.2.0)
Requires-Dist: sentencepiece (>=0.1.99,<0.2.0)
Requires-Dist: torch (>=2.1.2,<3.0.0)
Requires-Dist: tqdm (>=4.66.1,<5.0.0)
Requires-Dist: transformers (>=4.34.1,<5.0.0)
